<Properties StartupConfiguration="{DF9C09BE-B81C-4787-93E4-9D7702AD6C46}|Default">
  <MonoDevelop.Ide.Workspace ActiveConfiguration="Debug" />
  <MonoDevelop.Ide.DebuggingService.Breakpoints>
    <BreakpointStore />
  </MonoDevelop.Ide.DebuggingService.Breakpoints>
  <MonoDevelop.Ide.DebuggingService.PinnedWatches />
  <MonoDevelop.Ide.ItemProperties.WMS__Inventory__API PreferredExecutionTarget="/Applications/Google Chrome.app" />
  <MultiItemStartupConfigurations />
  <MonoDevelop.Ide.Workbench ActiveDocument="Controllers/AccountsController.cs">
    <Files>
      <File FileName="InventoryContext.cs" />
      <File FileName="Program.cs" Line="17" Column="1" />
      <File FileName="Controllers/AccountsController.cs" Line="46" Column="35" />
      <File FileName="Models/Account.cs" />
    </Files>
    <Pads>
      <Pad Id="ProjectPad">
        <State name="__root__">
          <Node name="WMS_Inventory_API" expanded="True">
            <Node name="WMS_Inventory_API" expanded="True">
              <Node name="Dependencies" expanded="True">
                <Node name="PackageDependencies" expanded="True" />
              </Node>
              <Node name="Controllers" expanded="True" />
              <Node name="Migrations" expanded="True" />
              <Node name="Models" expanded="True" />
              <Node name="Properties" expanded="True">
                <Node name="launchSettings.json" selected="True" />
              </Node>
            </Node>
          </Node>
        </State>
      </Pad>
    </Pads>
  </MonoDevelop.Ide.Workbench>
</Properties>